topstack_sdk/__init__.py
topstack_sdk/client.py
topstack_sdk/nats.py
topstack_sdk/alert/__init__.py
topstack_sdk/alert/alert.py
topstack_sdk/asset/__init__.py
topstack_sdk/asset/asset.py
topstack_sdk/datav/__init__.py
topstack_sdk/datav/datav.py
topstack_sdk/ems/__init__.py
topstack_sdk/ems/ems.py
topstack_sdk/iot/__init__.py
topstack_sdk/iot/iot.py
topstack_sdk/iot/models.py
topstack_sdk/iot/device/__init__.py
topstack_sdk/iot/device/device.py
topstack_sdk/iot/device/models.py
topstack_sdk-1.0.3.dist-info/licenses/LICENSE
topstack_sdk-1.0.3.dist-info/METADATA
topstack_sdk-1.0.3.dist-info/WHEEL
topstack_sdk-1.0.3.dist-info/top_level.txt
topstack_sdk-1.0.3.dist-info/RECORD
