Metadata-Version: 2.4
Name: topstack-sdk
Version: 1.0.3
Summary: TopStack Python SDK - 用于与 TopStack 平台交互的 Python 客户端库
Home-page: https://github.com/topstack/topstack-sdk-python
Author: TopStack Team
Author-email: TopStack Team <support@topstack.com>
Maintainer-email: TopStack Team <support@topstack.com>
License: MIT
Project-URL: Homepage, https://github.com/topstack/topstack-sdk-python
Project-URL: Documentation, https://github.com/topstack/topstack-sdk-python/blob/main/README.md
Project-URL: Repository, https://github.com/topstack/topstack-sdk-python
Project-URL: Bug Tracker, https://github.com/topstack/topstack-sdk-python/issues
Keywords: topstack,iot,api,client,sdk
Classifier: Development Status :: 4 - Beta
Classifier: Intended Audience :: Developers
Classifier: License :: OSI Approved :: MIT License
Classifier: Operating System :: OS Independent
Classifier: Programming Language :: Python :: 3
Classifier: Programming Language :: Python :: 3.7
Classifier: Programming Language :: Python :: 3.8
Classifier: Programming Language :: Python :: 3.9
Classifier: Programming Language :: Python :: 3.10
Classifier: Programming Language :: Python :: 3.11
Classifier: Topic :: Software Development :: Libraries :: Python Modules
Classifier: Topic :: System :: Networking
Classifier: Topic :: Internet :: WWW/HTTP :: HTTP Servers
Requires-Python: >=3.7
License-File: LICENSE
Requires-Dist: requests>=2.25.0
Requires-Dist: pydantic>=1.8.0
Requires-Dist: python-dateutil>=2.8.0
Requires-Dist: nats-py>=2.0.0
Provides-Extra: dev
Requires-Dist: pytest>=6.0; extra == "dev"
Requires-Dist: pytest-cov>=2.0; extra == "dev"
Requires-Dist: black>=21.0; extra == "dev"
Requires-Dist: flake8>=3.8; extra == "dev"
Requires-Dist: mypy>=0.800; extra == "dev"
Dynamic: author
Dynamic: home-page
Dynamic: license-file
Dynamic: requires-python
